mdi/__init__.py
mdi/libmdi.1.dylib
mdi/libmdi.dylib
mdi/mdi.h
mdi/mdi.mod
mdi/mdi.py
mdi/mdi_name
mdi/share/cmake/mdi/mdiConfig.cmake
mdi/share/cmake/mdi/mdiConfigVersion.cmake
mdi/share/cmake/mdi/mdiTargets-noconfig.cmake
mdi/share/cmake/mdi/mdiTargets.cmake
pymdi-1.2.6.dist-info/LICENSE
pymdi-1.2.6.dist-info/METADATA
pymdi-1.2.6.dist-info/WHEEL
pymdi-1.2.6.dist-info/top_level.txt
pymdi-1.2.6.dist-info/RECORD
