Metadata-Version: 2.1
Name: pymdi
Version: 1.2.6
Summary: A library that enables code interoperability via the MolSSI Driver Interface.
Home-page: https://github.com/MolSSI-MDI/MDI_Library
Author: Taylor Barnes
Author-email: info@molssi.org
License: BSD 3-clause
Platform: UNKNOWN
Classifier: Programming Language :: Python :: 3
Classifier: Programming Language :: Python :: 3.4
Classifier: Programming Language :: Python :: 3.5
Classifier: Programming Language :: Python :: 3.7
